matplotlib_latex_bridge/__init__.py
matplotlib_latex_bridge/formats.py
matplotlib_latex_bridge/matplotlib_latex_bridge.py
matplotlib_latex_bridge/version.py
matplotlib_latex_bridge-0.2.0.dist-info/COPYING
matplotlib_latex_bridge-0.2.0.dist-info/METADATA
matplotlib_latex_bridge-0.2.0.dist-info/WHEEL
matplotlib_latex_bridge-0.2.0.dist-info/top_level.txt
matplotlib_latex_bridge-0.2.0.dist-info/RECORD
