Metadata-Version: 2.1
Name: matplotlib-latex-bridge
Version: 0.2.0
Summary: Functions and shortcuts to create latex-ready images from matplotlib
Home-page: https://github.com/loreucci/matplotlib-latex-bridge
Author: Lorenzo Vannucci
Author-email: lore.ucci@gmail.com
License: UNKNOWN
Project-URL: Bug Tracker, https://github.com/loreucci/matplotlib-latex-bridge/issues
Platform: UNKNOWN
Classifier: Programming Language :: Python :: 3
Classifier: License :: OSI Approved :: GNU General Public License v3 or later (GPLv3+)
Classifier: Operating System :: OS Independent
Requires-Python: >=2.7
License-File: COPYING
Requires-Dist: matplotlib
